<annotation>
  <folder/>
  <filename>&#22270;&#29255;2775.jpg</filename>
  <database/>
  <annotation/>
  <image/>
  <size>
    <height>2000</height>
    <width>3300</width>
    <depth>3</depth>
  </size>
  <segmented/>
  <object>
    <name>ng</name>
    <pose/>
    <truncated/>
    <difficult/>
    <bndbox>
      <xmin>1287.313432835821</xmin>
      <ymin>1165.6716417910447</ymin>
      <xmax>1441.044776119403</xmax>
      <ymax>1200.0</ymax>
    </bndbox>
  </object>
  <object>
    <name>ng</name>
    <pose/>
    <truncated/>
    <difficult/>
    <bndbox>
      <xmin>2181.3765182186235</xmin>
      <ymin>587.8542510121457</ymin>
      <xmax>2314.1700404858298</xmax>
      <ymax>639.2712550607287</ymax>
    </bndbox>
  </object>
  <object>
    <name>ng</name>
    <pose/>
    <truncated/>
    <difficult/>
    <bndbox>
      <xmin>2314.97975708502</xmin>
      <ymin>595.1417004048583</ymin>
      <xmax>2554.655870445344</xmax>
      <ymax>802.4291497975707</ymax>
    </bndbox>
  </object>
</annotation>
