<annotation>
  <folder/>
  <filename>&#22270;&#29255;4024.jpg</filename>
  <database/>
  <annotation/>
  <image/>
  <size>
    <height>2000</height>
    <width>3300</width>
    <depth>3</depth>
  </size>
  <segmented/>
  <object>
    <name>ng</name>
    <pose/>
    <truncated/>
    <difficult/>
    <bndbox>
      <xmin>683.3898305084746</xmin>
      <ymin>548.3050847457627</ymin>
      <xmax>692.2033898305084</xmax>
      <ymax>558.8135593220338</ymax>
    </bndbox>
  </object>
  <object>
    <name>ng</name>
    <pose/>
    <truncated/>
    <difficult/>
    <bndbox>
      <xmin>1237.9781420765028</xmin>
      <ymin>745.0819672131147</ymin>
      <xmax>1395.9016393442623</xmax>
      <ymax>779.7814207650273</ymax>
    </bndbox>
  </object>
  <object>
    <name>ng</name>
    <pose/>
    <truncated/>
    <difficult/>
    <bndbox>
      <xmin>2116.4</xmin>
      <ymin>1011.6</ymin>
      <xmax>2128.528072837633</xmax>
      <ymax>1056.9044006069803</ymax>
    </bndbox>
  </object>
  <object>
    <name>ng</name>
    <pose/>
    <truncated/>
    <difficult/>
    <bndbox>
      <xmin>1978.2563025210086</xmin>
      <ymin>1091.9117647058824</ymin>
      <xmax>1982.3728813559321</xmax>
      <ymax>1106.1016949152543</ymax>
    </bndbox>
  </object>
  <object>
    <name>ng</name>
    <pose/>
    <truncated/>
    <difficult/>
    <bndbox>
      <xmin>2055.7</xmin>
      <ymin>1089.4</ymin>
      <xmax>2065.8</xmax>
      <ymax>1102.9</ymax>
    </bndbox>
  </object>
  <object>
    <name>ng</name>
    <pose/>
    <truncated/>
    <difficult/>
    <bndbox>
      <xmin>1877.5</xmin>
      <ymin>1494.4444444444443</ymin>
      <xmax>1889.1666666666665</xmax>
      <ymax>1545.2777777777778</ymax>
    </bndbox>
  </object>
</annotation>
